LICENSE
MANIFEST.in
README.md
RELEASE-VERSION
setup.py
version.py
miniwdl_aws/__init__.py
miniwdl_aws/__main__.py
miniwdl_aws/_util.py
miniwdl_aws/batch_job.py
miniwdl_aws/cli_run_s3upload.py
miniwdl_aws/cli_submit.py
miniwdl_aws.egg-info/PKG-INFO
miniwdl_aws.egg-info/SOURCES.txt
miniwdl_aws.egg-info/dependency_links.txt
miniwdl_aws.egg-info/entry_points.txt
miniwdl_aws.egg-info/requires.txt
miniwdl_aws.egg-info/top_level.txt
test/test.py