Metadata-Version: 2.1
Name: miniwdl-aws
Version: 0.4.0
Summary: miniwdl AWS backend (Batch+EFS)
Author: Wid L. Hacker
License: UNKNOWN
Platform: UNKNOWN
Requires-Python: >=3.6
License-File: LICENSE
